setup.py
sensu/__init__.py
sensu/handler.py
sensu/utils.py
sensu.egg-info/PKG-INFO
sensu.egg-info/SOURCES.txt
sensu.egg-info/dependency_links.txt
sensu.egg-info/requires.txt
sensu.egg-info/top_level.txt