Metadata-Version: 1.1
Name: sensu
Version: 0.0.2
Summary: Python plugin for the Sensu monitoring framework
Home-page: http://github.com/ehazlett/sensu-py
Author: Evan Hazlett
Author-email: ejhazlett@gmail.com
License: MIT
Download-URL: https://github.com/ehazlett/sensu-py/zipball/0.0.2
Keywords: sensu,plugin,monitoring
Platform: UNKNOWN
Classifier: Environment :: Console
Classifier: Intended Audience :: Developers
Classifier: License :: OSI Approved :: MIT License
Classifier: Operating System :: OS Independent
Classifier: Programming Language :: Python
Classifier: Programming Language :: Python :: 2.7
